dbt_run_analyser/__init__.py
dbt_run_analyser/dag.py
dbt_run_analyser/node.py
dbt_run_analyser/plot.py
dbt_run_analyser/cli/__init__.py
dbt_run_analyser/cli/main.py
dbt_run_analyser/cli/params.py
dbt_run_analyser/utils/__init__.py
dbt_run_analyser/utils/log_parser.py
dbt_run_analyser/utils/manifest_parser.py
dbt_run_analyser-0.3.1.dist-info/METADATA
dbt_run_analyser-0.3.1.dist-info/WHEEL
dbt_run_analyser-0.3.1.dist-info/entry_points.txt
dbt_run_analyser-0.3.1.dist-info/licenses/LICENSE
dbt_run_analyser-0.3.1.dist-info/RECORD
