Metadata-Version: 2.4
Name: dbt_run_analyser
Version: 0.3.1
Summary: Python library to analyse thread utilisation for dbt runs.
Project-URL: Homepage, https://github.com/mathiasDK/dbt-run-analyser
Author-email: Mathias Nørskov <mathiasnoerskov@gmail.com>
License: MIT
License-File: LICENSE
Keywords: dbt_run_analyser
Classifier: Development Status :: 4 - Beta
Classifier: Intended Audience :: Science/Research
Classifier: License :: OSI Approved :: Apache Software License
Classifier: Natural Language :: English
Classifier: Programming Language :: Python :: 3.8
Classifier: Programming Language :: Python :: 3.9
Classifier: Programming Language :: Python :: 3.10
Requires-Python: <4,>=3.8
Requires-Dist: click
Requires-Dist: pandas>=2.2
Requires-Dist: plotly>=6.0
Requires-Dist: polars>=1.0
Provides-Extra: test
Requires-Dist: black==24.*; extra == 'test'
Requires-Dist: coverage-badge==1.*; extra == 'test'
Requires-Dist: coverage==7.2.2; extra == 'test'
Requires-Dist: dbt-core==1.9.1; extra == 'test'
Requires-Dist: dbt-duckdb==1.9.1; extra == 'test'
Requires-Dist: flake8==4.0.1; extra == 'test'
Requires-Dist: pytest-cov==4.0.0; extra == 'test'
Requires-Dist: pytest==8.*; extra == 'test'
Requires-Dist: tox==4.4.7; extra == 'test'
Requires-Dist: twine==4.0.0; extra == 'test'
